jobtastic/__init__.py
jobtastic/states.py
jobtastic/task.py
jobtastic/cache/__init__.py
jobtastic/cache/base.py
jobtastic/tests/__init__.py
jobtastic/tests/test_broker_fallbacks.py
jobtastic/tests/test_memleak_detection.py
jobtastic/tests/test_progress.py
jobtastic/tests/test_settings.py
jobtastic-2.1.1.dist-info/AUTHORS
jobtastic-2.1.1.dist-info/LICENSE
jobtastic-2.1.1.dist-info/METADATA
jobtastic-2.1.1.dist-info/WHEEL
jobtastic-2.1.1.dist-info/top_level.txt
jobtastic-2.1.1.dist-info/RECORD
