Metadata-Version: 2.1
Name: jobtastic
Version: 2.1.1
Summary: Make your user-facing Celery jobs totally awesomer
Home-page: http://policystat.github.com/jobtastic
Author: Wes Winham
Author-email: winhamwr@gmail.com
License: BSD
Platform: any
Classifier: Development Status :: 4 - Beta
Classifier: Intended Audience :: Developers
Classifier: License :: OSI Approved :: MIT License
Classifier: Topic :: System :: Distributed Computing
Classifier: Topic :: Software Development :: Object Brokering
Classifier: Programming Language :: Python
Classifier: Programming Language :: Python :: 2.6
Classifier: Programming Language :: Python :: 2.7
Classifier: Operating System :: OS Independent
Classifier: Operating System :: POSIX
Classifier: Operating System :: Microsoft :: Windows
Classifier: Operating System :: MacOS :: MacOS X
Classifier: Framework :: Django
Requires-Dist: psutil
Requires-Dist: celery (<5,>=3.1)
